sdap_ingest_manager/__init__.py
sdap_ingest_manager/collections_ingester/__init__.py
sdap_ingest_manager/collections_ingester/collection_ingestion.py
sdap_ingest_manager/collections_ingester/google_spreadsheet_collection_config.py
sdap_ingest_manager/collections_ingester/nfs_mount_parse.py
sdap_ingest_manager/collections_ingester/util.py
sdap_ingest_manager/collections_ingester/yaml_file_collection_config.py
sdap_ingest_manager/collections_ingester/resources/dataset_config_template.yml
sdap_ingest_manager/collections_ingester/resources/config/collections.yml.example
sdap_ingest_manager/collections_ingester/resources/config/credentials.json.template
sdap_ingest_manager/collections_ingester/resources/config/sdap_ingest_manager.ini.default
sdap_ingest_manager/collections_ingester/test/__init__.py
sdap_ingest_manager/collections_ingester/test/data/avhrr_oi/20151101120000-NCEI-L4_GHRSST-SSTblend-AVHRR_OI-GLOB-v02.0-fv02.0.nc
sdap_ingest_manager/collections_ingester/test/data/avhrr_oi/20151102120000-NCEI-L4_GHRSST-SSTblend-AVHRR_OI-GLOB-v02.0-fv02.0.nc
sdap_ingest_manager/collections_ingester/test/unit/__init__.py
sdap_ingest_manager/collections_ingester/test/unit/collection_ingestion_test.py
sdap_ingest_manager/collections_ingester/test/unit/nfs_mount_parse_test.py
sdap_ingest_manager/collections_ingester/test/unit/util_test.py
sdap_ingest_manager/collections_ingester/test/unit/yaml_file_collection_config_test.py
sdap_ingest_manager/collections_ingester/test/validation/__init__.py
sdap_ingest_manager/collections_ingester/test/validation/validation_test.py
sdap_ingest_manager/granule_ingester/__init__.py
sdap_ingest_manager/granule_ingester/runjobs.py
sdap_ingest_manager/granule_ingester/solringestionhistory.py
sdap_ingest_manager/granule_ingester/resources/connection-config.yml
sdap_ingest_manager/granule_ingester/resources/job-deployment-template.yml
sdap_ingest_manager/history_manager/__init__.py
sdap_ingest_manager/history_manager/datasetingestionhistoryfile.py
sdap_ingest_manager-0.3.0rc3.dist-info/LICENSE.txt
sdap_ingest_manager-0.3.0rc3.dist-info/METADATA
sdap_ingest_manager-0.3.0rc3.dist-info/WHEEL
sdap_ingest_manager-0.3.0rc3.dist-info/top_level.txt
sdap_ingest_manager-0.3.0rc3.dist-info/RECORD
