Metadata-Version: 2.1
Name: sdap-ingest-manager
Version: 0.3.0rc3
Summary: a helper to ingest data in sdap
Home-page: https://github.com/tloubrieu-jpl/incubator-sdap-nexus-ingestion-manager
Author: Apache - SDAP
Author-email: dev@sdap.apache.org
License: UNKNOWN
Platform: UNKNOWN
Classifier: Programming Language :: Python :: 3
Classifier: Operating System :: OS Independent
Classifier: Development Status :: 4 - Beta
Requires-Python: >=3.6
Requires-Dist: google-api-python-client (>=1.7)
Requires-Dist: google-auth-oauthlib (>=0.4)
Requires-Dist: pystache (>=0.5)
Requires-Dist: pyyaml
Requires-Dist: pysolr (>=3.8)
